subaligner/__init__.py
subaligner/__main__.py
subaligner/_version.py
subaligner/embedder.py
subaligner/exception.py
subaligner/hparam_tuner.py
subaligner/hyperparameters.py
subaligner/llm.py
subaligner/logger.py
subaligner/media_helper.py
subaligner/network.py
subaligner/predictor.py
subaligner/singleton.py
subaligner/subtitle.py
subaligner/trainer.py
subaligner/transcriber.py
subaligner/translator.py
subaligner/utils.py
subaligner/lib/__init__.py
subaligner/lib/language.py
subaligner/lib/to_srt.py
subaligner/models/training/config/hyperparameters.json
subaligner/models/training/model/__init__.py
subaligner/models/training/model/combined.h5
subaligner/models/training/model/combined.hdf5
subaligner/models/training/model/model.h5
subaligner/models/training/model/model.hdf5
subaligner/models/training/weights/__init__.py
subaligner/models/training/weights/weights.h5
subaligner/models/training/weights/weights.hdf5
subaligner/subaligner_1pass/__init__.py
subaligner/subaligner_1pass/__main__.py
subaligner/subaligner_2pass/__init__.py
subaligner/subaligner_2pass/__main__.py
subaligner/subaligner_batch/__init__.py
subaligner/subaligner_batch/__main__.py
subaligner/subaligner_convert/__init__.py
subaligner/subaligner_convert/__main__.py
subaligner/subaligner_train/__init__.py
subaligner/subaligner_train/__main__.py
subaligner/subaligner_tune/__init__.py
subaligner/subaligner_tune/__main__.py
subaligner-0.3.11.dist-info/LICENSE
subaligner-0.3.11.dist-info/METADATA
subaligner-0.3.11.dist-info/WHEEL
subaligner-0.3.11.dist-info/entry_points.txt
subaligner-0.3.11.dist-info/top_level.txt
subaligner-0.3.11.dist-info/RECORD
