Metadata-Version: 2.1
Name: subaligner
Version: 0.3.11
Summary: Automatically synchronize and translate subtitles, or create new ones by transcribing, using pre-trained DNNs, Forced Alignments and Transformers.
Author-email: Xi Bai <xi.bai.ed@gmail.com>
Project-URL: Homepage, https://github.com/baxtree/subaligner
Project-URL: Documentation, https://subaligner.readthedocs.io/en/latest/
Project-URL: Source, https://github.com/baxtree/subaligner
Classifier: License :: OSI Approved :: MIT License
Classifier: Programming Language :: Python :: 3.12
Classifier: Programming Language :: Python :: 3.11
Classifier: Programming Language :: Python :: 3.10
Classifier: Programming Language :: Python :: 3.9
Classifier: Programming Language :: Python :: 3.8
Classifier: Intended Audience :: Developers
Classifier: Topic :: Utilities
Requires-Python: <3.13,>=3.8
License-File: LICENSE
Requires-Dist: astor==0.7.1
Requires-Dist: beautifulsoup4<4.9.0
Requires-Dist: bleach==3.3.0
Requires-Dist: cachetools==3.1.1
Requires-Dist: captionstransformer~=1.2.1
Requires-Dist: certifi<2024.12.14
Requires-Dist: chardet~=3.0.4
Requires-Dist: cloudpickle~=1.6.0
Requires-Dist: cycler==0.10.0
Requires-Dist: decorator==4.3.0
Requires-Dist: distributed==2021.10.0
Requires-Dist: filelock<4.0.0
Requires-Dist: google-pasta~=0.2
Requires-Dist: graphviz==0.8.3
Requires-Dist: HeapDict==1.0.0
Requires-Dist: h5py<4.0.0
Requires-Dist: html5lib==1.0b9
Requires-Dist: hyperopt==0.2.4
Requires-Dist: idna<3.9
Requires-Dist: isort==4.3.4
Requires-Dist: joblib>=1.2.0
Requires-Dist: le-pycaption==2.2.0a1
Requires-Dist: librosa<0.10.0
Requires-Dist: locket==0.2.0
Requires-Dist: Markdown==2.6.11
Requires-Dist: mccabe==0.6.1
Requires-Dist: networkx>=2.5.1
Requires-Dist: numba<0.62.0,>=0.50.0
Requires-Dist: numpy<1.27.0
Requires-Dist: oauthlib==3.1.0
Requires-Dist: pbr==4.0.2
Requires-Dist: pkgconfig~=1.5.5
Requires-Dist: platformdirs<4.0.0
Requires-Dist: pluggy==0.13.1
Requires-Dist: psutil~=7.0.0
Requires-Dist: pyasn1==0.4.8
Requires-Dist: pyasn1-modules==0.2.7
Requires-Dist: pybind11~=2.11.1
Requires-Dist: pycountry~=20.7.3
Requires-Dist: pydot==1.2.4
Requires-Dist: pydot-ng==1.0.0
Requires-Dist: pydotplus==2.0.2
Requires-Dist: pyprof2calltree==1.4.3
Requires-Dist: pysrt==1.1.2
Requires-Dist: pysubs2~=1.6.1
Requires-Dist: pytz==2018.4
Requires-Dist: PyYAML>=4.2b1
Requires-Dist: rsa==4.7
Requires-Dist: scipy<1.12.0
Requires-Dist: termcolor==1.1.0
Requires-Dist: toml==0.10.0
Requires-Dist: toolz==0.9.0
Requires-Dist: urllib3~=1.26.5
Requires-Dist: wrapt==1.14.0
Requires-Dist: Werkzeug>=0.15.3
Requires-Dist: zict==0.1.3
Requires-Dist: scikit-learn<1.2.0; python_version < "3.12"
Requires-Dist: six~=1.15.0; python_version < "3.12"
Requires-Dist: tensorflow<2.16.0,>=1.15.5; python_version < "3.12"
Requires-Dist: scikit-learn>=1.2.0; python_version >= "3.12"
Requires-Dist: six~=1.17.0; python_version >= "3.12"
Requires-Dist: tf-keras~=2.19.0; python_version >= "3.12"
Requires-Dist: tensorflow~=2.19.0; python_version >= "3.12"
Provides-Extra: dev
Requires-Dist: dtw-python~=1.5.3; extra == "dev"
Requires-Dist: safetensors~=0.5.3; extra == "dev"
Requires-Dist: torch<2.3.0; extra == "dev"
Requires-Dist: torchaudio<2.3.0; extra == "dev"
Requires-Dist: transformers<4.37.0; extra == "dev"
Requires-Dist: openai-whisper==20250625; extra == "dev"
Requires-Dist: mock==4.0.3; extra == "dev"
Requires-Dist: coverage==5.5; extra == "dev"
Requires-Dist: tox~=3.23.0; extra == "dev"
Requires-Dist: pycodestyle==2.12.1; extra == "dev"
Requires-Dist: twine<3.8.0; extra == "dev"
Requires-Dist: snakeviz==2.1.0; extra == "dev"
Requires-Dist: line-profiler~=4.1.2; extra == "dev"
Requires-Dist: scikit-build==0.11.1; extra == "dev"
Requires-Dist: radish-bdd~=0.13.3; extra == "dev"
Requires-Dist: pex<=2.1.80; extra == "dev"
Requires-Dist: mypy==1.3.0; extra == "dev"
Requires-Dist: types-requests==2.27.9; extra == "dev"
Requires-Dist: types-setuptools==64.0.1; extra == "dev"
Requires-Dist: typing-extensions==4.8.0; extra == "dev"
Requires-Dist: parameterized==0.8.1; extra == "dev"
Requires-Dist: pylint~=2.17.2; extra == "dev"
Requires-Dist: pygments<3.0.0; extra == "dev"
Requires-Dist: darglint~=1.8.1; extra == "dev"
Requires-Dist: aeneas~=1.7.3.0; python_version < "3.12" and extra == "dev"
Requires-Dist: sentencepiece~=0.1.95; python_version < "3.12" and extra == "dev"
Requires-Dist: sentencepiece~=0.2.0; python_version >= "3.12" and extra == "dev"
Provides-Extra: docs
Requires-Dist: sphinx==6.2.1; extra == "docs"
Requires-Dist: sphinx-rtd-theme==2.0.0; extra == "docs"
Requires-Dist: docutils<0.22; extra == "docs"
Provides-Extra: harmony
Requires-Dist: dtw-python~=1.5.3; extra == "harmony"
Requires-Dist: safetensors~=0.5.3; extra == "harmony"
Requires-Dist: torch<2.3.0; extra == "harmony"
Requires-Dist: torchaudio<2.3.0; extra == "harmony"
Requires-Dist: transformers<4.37.0; extra == "harmony"
Requires-Dist: openai-whisper==20250625; extra == "harmony"
Requires-Dist: aeneas~=1.7.3.0; python_version < "3.12" and extra == "harmony"
Requires-Dist: sentencepiece~=0.1.95; python_version < "3.12" and extra == "harmony"
Requires-Dist: sentencepiece~=0.2.0; python_version >= "3.12" and extra == "harmony"
Provides-Extra: llm
Requires-Dist: safetensors~=0.5.3; extra == "llm"
Requires-Dist: torch<2.3.0; extra == "llm"
Requires-Dist: torchaudio<2.3.0; extra == "llm"
Requires-Dist: transformers<4.37.0; extra == "llm"
Requires-Dist: openai-whisper==20250625; extra == "llm"
Requires-Dist: sentencepiece~=0.1.95; python_version < "3.12" and extra == "llm"
Requires-Dist: sentencepiece~=0.2.0; python_version >= "3.12" and extra == "llm"
Provides-Extra: stretch
Requires-Dist: dtw-python~=1.5.3; extra == "stretch"
Requires-Dist: aeneas~=1.7.3.0; python_version < "3.12" and extra == "stretch"
